sysetup/__init__.py
sysetup/py.typed
sysetup/cli/__init__.py
sysetup/cli/entry_point.py
sysetup/context/__init__.py
sysetup/context/action.py
sysetup/context/context.py
sysetup/context/installations.py
sysetup/context/options.py
sysetup/context/secrets_.py
sysetup/main/__init__.py
sysetup/main/installations.py
sysetup/main/main.py
sysetup/main/packages.py
sysetup/main/files/__init__.py
sysetup/main/files/assets.py
sysetup/main/files/permissions.py
sysetup/main/files/settings.py
sysetup/main/files/setup.py
sysetup/models/__init__.py
sysetup/models/path.py
sysetup/utils/__init__.py
sysetup/utils/bitwarden.py
sysetup/utils/download.py
sysetup-1.4.3.data/scripts/pw
sysetup-1.4.3.data/scripts/pw-askpass
sysetup-1.4.3.dist-info/licenses/LICENSE
sysetup-1.4.3.dist-info/METADATA
sysetup-1.4.3.dist-info/WHEEL
sysetup-1.4.3.dist-info/entry_points.txt
sysetup-1.4.3.dist-info/top_level.txt
sysetup-1.4.3.dist-info/RECORD
