Metadata-Version: 2.4
Name: sysetup
Version: 1.4.3
Summary: Personal system setup
Author-email: Quinten Roets <qdr2104@columbia.edu>
License-Expression: MIT
Project-URL: Source Code, https://github.com/quintenroets/sysetup
Requires-Python: >=3.10
License-File: LICENSE
Requires-Dist: backupmaster<3,>=2.0.2
Requires-Dist: dbus-next<1,>=0.2.3
Requires-Dist: package-utils[context]<1,>=0.6.1
Requires-Dist: powercli<1,>=0.3.1
Requires-Dist: requests<3,>=2.32.3
Requires-Dist: superpathlib<3,>=2.0.4
Provides-Extra: dev
Requires-Dist: dirhash<1,>=0.5.0; extra == "dev"
Requires-Dist: types-requests<3,>=2.32.0.20250306; extra == "dev"
Requires-Dist: package-dev-tools<1,>=0.7.1; extra == "dev"
Requires-Dist: package-dev-utils<1,>=0.1.6; extra == "dev"
Dynamic: license-file
